<?xml version="1.0" encoding="UTF-8"?><artifacts>
    <artifact name="GovAPI" groupId="com.example.ApiToCSV.api" version="1.0.0" type="synapse/api" serverRole="EnterpriseServiceBus">
        <file>src/main/synapse-config/api/GovAPI.xml</file>
    </artifact>
    <artifact name="CopyTofile" groupId="com.example.ApiToCSV.endpoint" version="1.0.0" type="synapse/endpoint" serverRole="EnterpriseServiceBus">
        <file>src/main/synapse-config/endpoints/CopyTofile.xml</file>
    </artifact>
</artifacts>
